sksdkfdkTest/test1.py
sksdkfdkTest/test2.py
sksdkfdkTest-0.0.0.1.dist-info/METADATA
sksdkfdkTest-0.0.0.1.dist-info/WHEEL
sksdkfdkTest-0.0.0.1.dist-info/top_level.txt
sksdkfdkTest-0.0.0.1.dist-info/RECORD
