Metadata-Version: 2.1
Name: sksdkfdkTest
Version: 0.0.0.1
Summary: My First Test Package(BMI)
Home-page: UNKNOWN
Author: 99Night
Author-email: dhralsdlsl14@naver.com
License: MIT
Platform: UNKNOWN
Requires-Python: >=3
